ebooks_lister/__init__.py
ebooks_lister/cli.py
ebooks_lister/ebooks_lister.py
ebooks_lister-0.1.0.dist-info/entry_points.txt
ebooks_lister-0.1.0.dist-info/LICENSE
ebooks_lister-0.1.0.dist-info/WHEEL
ebooks_lister-0.1.0.dist-info/METADATA
ebooks_lister-0.1.0.dist-info/RECORD
